{
  "projectId": "gen-lang-client-0249032212",
  "appId": "1:403384727705:web:1e09d6a98a93cac715e008",
  "apiKey": "AIzaSyAVbR7T_d1uzqZNnvPYeNVItflDbhKTtOc",
  "authDomain": "gen-lang-client-0249032212.firebaseapp.com",
  "firestoreDatabaseId": "ai-studio-consistencystrat-2751ff16-a223-40bc-a42d-6234c3c30b16",
  "storageBucket": "gen-lang-client-0249032212.firebasestorage.app",
  "messagingSenderId": "403384727705",
  "measurementId": "",
  "oAuthClientId": "403384727705-68b8derjp77l6b3uiqe2o70limf4hd62.apps.googleusercontent.com"
}